cnstats/__init__.py
cnstats/__main__.py
cnstats/cache.py
cnstats/dbcode.py
cnstats/easyquery.py
cnstats/quicktypes.py
cnstats_py-0.0.4.dist-info/licenses/LICENSE
cnstats_py-0.0.4.dist-info/METADATA
cnstats_py-0.0.4.dist-info/WHEEL
cnstats_py-0.0.4.dist-info/top_level.txt
cnstats_py-0.0.4.dist-info/RECORD
