Metadata-Version: 2.4
Name: cnstats-py
Version: 0.0.4
Summary: Download macroeconomic data from China's National Bureau of Statistics (data.stats.gov.cn).
Author-email: Clsrfish <clsrfish@gmail.com>
Project-URL: Homepage, https://github.com/clsrfish/cnstats-py
Project-URL: Bug Tracker, https://github.com/clsrfish/cnstats-py/issues
Classifier: Programming Language :: Python :: 3
Classifier: License :: OSI Approved :: MIT License
Classifier: Operating System :: OS Independent
Requires-Python: >=3.7
License-File: LICENSE
Requires-Dist: requests
Requires-Dist: pandas
Provides-Extra: excel
Requires-Dist: openpyxl; extra == "excel"
Provides-Extra: dev
Requires-Dist: black; extra == "dev"
Requires-Dist: pytest; extra == "dev"
Requires-Dist: build; extra == "dev"
Requires-Dist: twine; extra == "dev"
Dynamic: license-file
